MANIFEST.in
README.rst
setup.cfg
setup.py
ocms16S/PipelineDada2.py
ocms16S/__init__.py
ocms16S/ocms_16s.py
ocms16S/pipeline_dada2.py
ocms16S/pipeline_help.py
ocms16S/R/._dada2_assign_taxonomy.R
ocms16S/R/dada2_assign_taxonomy.R
ocms16S/R/dada2_filter_and_trim.R
ocms16S/R/dada2_helper.R
ocms16S/R/dada2_sample_inference.R
ocms16S/R/dada2_split_levels.R
ocms16S/R/render.R
ocms16S/pipeline_dada2/pipeline.yml
ocms16S/pipeline_docs/Rmd/pipeline_dada2/pipeline_dada2.Rmd
ocms16S/pipeline_docs/Rmd/pipeline_dada2/pipeline_dada2_diagnostics.Rmd
ocms16S/pipeline_docs/Rmd/pipeline_dada2/report.Rmd
ocms16S/scripts/combine_tables.py
ocms_16S.egg-info/PKG-INFO
ocms_16S.egg-info/SOURCES.txt
ocms_16S.egg-info/dependency_links.txt
ocms_16S.egg-info/entry_points.txt
ocms_16S.egg-info/requires.txt
ocms_16S.egg-info/top_level.txt